README.md
setup.py
pyqtcolordialog/__init__.py
pyqtcolordialog/__main__.py
pyqtcolordialog/color_dialog.py
pyqtcolordialog/color_model.py
pyqtcolordialog/color_preview.py
pyqtcolordialog/color_ring.py
pyqtcolordialog/color_sliders.py
pyqtcolordialog/color_square.py
pyqtcolordialog/geometry.py
pyqtcolordialog/grid.png
pyqtcolordialog/screen_color_picker.py
pyqtcolordialog/util.py
pyqtcolordialog.egg-info/PKG-INFO
pyqtcolordialog.egg-info/SOURCES.txt
pyqtcolordialog.egg-info/dependency_links.txt
pyqtcolordialog.egg-info/requires.txt
pyqtcolordialog.egg-info/top_level.txt
pyqtcolordialog/../LICENSE.md